LICENSE.txt
MANIFEST.in
README.md
README.pypi
pyproject.toml
setup.py
doc/Makefile
doc/conf.py
doc/index.rst
doc/make.bat
doc/_build/html/.buildinfo
doc/_build/html/genindex.html
doc/_build/html/index.html
doc/_build/html/objects.inv
doc/_build/html/search.html
doc/_build/html/searchindex.js
doc/_build/html/_images/Explain-Model-Example.png
doc/_build/html/_images/Explain-Model.png
doc/_build/html/_images/Explain-Prediction-Example.png
doc/_build/html/_images/Explain-Prediction.png
doc/_build/html/_images/ICE-example.png
doc/_build/html/_images/ICE.png
doc/_build/html/_images/Permutation-Importance-Example.png
doc/_build/html/_images/Permutation-Importance.png
doc/_build/html/_sources/index.rst.txt
doc/_build/html/_sources/widgets/explain-model.md.txt
doc/_build/html/_sources/widgets/explain-prediction.md.txt
doc/_build/html/_sources/widgets/explain-predictions.md.txt
doc/_build/html/_sources/widgets/ice.md.txt
doc/_build/html/_sources/widgets/permutation-importance.md.txt
doc/_build/html/_static/basic.css
doc/_build/html/_static/custom.css
doc/_build/html/_static/doctools.js
doc/_build/html/_static/documentation_options.js
doc/_build/html/_static/file.png
doc/_build/html/_static/language_data.js
doc/_build/html/_static/minus.png
doc/_build/html/_static/plus.png
doc/_build/html/_static/pygments.css
doc/_build/html/_static/searchtools.js
doc/_build/html/_static/sphinx_highlight.js
doc/_build/html/_static/css/badge_only.css
doc/_build/html/_static/css/theme.css
doc/_build/html/_static/css/fonts/Roboto-Slab-Bold.woff
doc/_build/html/_static/css/fonts/Roboto-Slab-Bold.woff2
doc/_build/html/_static/css/fonts/Roboto-Slab-Regular.woff
doc/_build/html/_static/css/fonts/Roboto-Slab-Regular.woff2
doc/_build/html/_static/css/fonts/fontawesome-webfont.eot
doc/_build/html/_static/css/fonts/fontawesome-webfont.svg
doc/_build/html/_static/css/fonts/fontawesome-webfont.ttf
doc/_build/html/_static/css/fonts/fontawesome-webfont.woff
orange3_explain_numpy2.egg-info/PKG-INFO
orange3_explain_numpy2.egg-info/SOURCES.txt
orange3_explain_numpy2.egg-info/dependency_links.txt
orange3_explain_numpy2.egg-info/entry_points.txt
orange3_explain_numpy2.egg-info/namespace_packages.txt
orange3_explain_numpy2.egg-info/not-zip-safe
orange3_explain_numpy2.egg-info/requires.txt
orange3_explain_numpy2.egg-info/top_level.txt
