Metadata-Version: 2.1
Name: orange3-explain-numpy2
Version: 0.6.10
Summary: Orange3 add-on for explanatory AI
Home-page: https://orangedatamining.com/download
Author: 
Author-email: 
License: GPL3+
Keywords: orange3 add-on,orange3-explain
Classifier: Development Status :: 4 - Beta
Classifier: Intended Audience :: Science/Research
Classifier: Programming Language :: Python :: 3 :: Only
Provides-Extra: test
Provides-Extra: doc
License-File: LICENSE.txt
